deepAntigen/__init__.py
deepAntigen/antigenHLAI/__init__.py
deepAntigen/antigenHLAI/config_atom.ini
deepAntigen/antigenHLAI/config_seq.ini
deepAntigen/antigenHLAI/run_antigenHLAI_atom.py
deepAntigen/antigenHLAI/run_antigenHLAI_seq.py
deepAntigen/antigenHLAI/Weights/atom-level_parameters.pt
deepAntigen/antigenHLAI/Weights/seq-level_parameters.pt
deepAntigen/antigenHLAI/load_dataset/__init__.py
deepAntigen/antigenHLAI/load_dataset/featurizer.py
deepAntigen/antigenHLAI/load_dataset/hlaI_pseudo_seq.csv
deepAntigen/antigenHLAI/load_dataset/load_seq.py
deepAntigen/antigenHLAI/load_dataset/load_structure.py
deepAntigen/antigenHLAI/networks/__init__.py
deepAntigen/antigenHLAI/networks/pHLAI_atom.py
deepAntigen/antigenHLAI/networks/pHLAI_seq.py
deepAntigen/antigenHLAI/networks/top_k_pooling_atom.py
deepAntigen/antigenHLAI/networks/top_k_pooling_seq.py
deepAntigen/antigenHLAI/utils/__init__.py
deepAntigen/antigenHLAI/utils/antigenHLAI_preprocess.py
deepAntigen/antigenHLAI/utils/model_utils.py
deepAntigen/antigenHLAII/__init__.py
deepAntigen/antigenHLAII/config_atom.ini
deepAntigen/antigenHLAII/config_seq.ini
deepAntigen/antigenHLAII/run_antigenHLAII_atom.py
deepAntigen/antigenHLAII/run_antigenHLAII_seq.py
deepAntigen/antigenHLAII/Weights/atom-level_parameters.pt
deepAntigen/antigenHLAII/Weights/seq-level_parameters.pt
deepAntigen/antigenHLAII/load_dataset/__init__.py
deepAntigen/antigenHLAII/load_dataset/featurizer.py
deepAntigen/antigenHLAII/load_dataset/hlaII_pseudo_seq.csv
deepAntigen/antigenHLAII/load_dataset/load_seq.py
deepAntigen/antigenHLAII/load_dataset/load_structure.py
deepAntigen/antigenHLAII/networks/__init__.py
deepAntigen/antigenHLAII/networks/pHLAII_atom.py
deepAntigen/antigenHLAII/networks/pHLAII_seq.py
deepAntigen/antigenHLAII/networks/top_k_pooling_atom.py
deepAntigen/antigenHLAII/networks/top_k_pooling_seq.py
deepAntigen/antigenHLAII/utils/__init__.py
deepAntigen/antigenHLAII/utils/antigenHLAII_preprocess.py
deepAntigen/antigenHLAII/utils/model_utils.py
deepAntigen-1.0.3.dist-info/LICENSE
deepAntigen-1.0.3.dist-info/METADATA
deepAntigen-1.0.3.dist-info/WHEEL
deepAntigen-1.0.3.dist-info/top_level.txt
deepAntigen-1.0.3.dist-info/RECORD
