Metadata-Version: 2.1
Name: deepAntigen
Version: 1.0.3
Summary: Identifying T cell antigen at the atomic level with graph convolutional network
Home-page: https://github.com/JiangBioLab/deepAntigen
Author: JinhaoQue
Author-email: quejinhao2021@163.com
License: MIT License
Keywords: T cell antigen,atom-level,GCN
Classifier: Programming Language :: Python :: 3.8
Classifier: License :: OSI Approved :: MIT License
Classifier: Operating System :: OS Independent
Requires-Python: >=3.8
License-File: LICENSE
Requires-Dist: pygments>=2.17.2
Requires-Dist: importlib-metadata>=7.1.0
Requires-Dist: typing-extensions>=4.5.0
Requires-Dist: requests>=2.20
Requires-Dist: urllib3>=1.26.0
Requires-Dist: deepchem>=2.6.1
Requires-Dist: biopython>=1.83
Requires-Dist: rdkit>=2023.9.5
Requires-Dist: seaborn>=0.13.2
Requires-Dist: matplotlib>=3.7.5
